<?xml version="1.0" encoding="UTF-8"?>
<!DOCTYPE xliff PUBLIC "-//XLIFF//DTD XLIFF//EN" "http://www.oasis-open.org/committees/xliff/documents/xliff.dtd">
<xliff version="1.0">
    <file source-language="EN" target-language="ru" datatype="plaintext" original="messages" date="2012-10-25T14:49:43Z" product-name="messages">
        <header/>
        <body>
            <trans-unit>
                <source>Monday</source>
                <target>Понедельник</target>
            </trans-unit>
            <trans-unit>
                <source>Tuesday</source>
                <target>Вторник</target>
            </trans-unit>
            <trans-unit>
                <source>Wednesday</source>
                <target>Среда</target>
            </trans-unit>
            <trans-unit>
                <source>Thursday</source>
                <target>Четверг</target>
            </trans-unit>
            <trans-unit>
                <source>Friday</source>
                <target>Пятница</target>
            </trans-unit>
            <trans-unit>
                <source>Saturday</source>
                <target>Суббота</target>
            </trans-unit>
            <trans-unit>
                <source>Sunday</source>
                <target>Воскресенье</target>
            </trans-unit>

            <trans-unit>
                <source>January</source>
                <target>Января</target>
            </trans-unit>
            <trans-unit>
                <source>February</source>
                <target>Февраля</target>
            </trans-unit>
            <trans-unit>
                <source>March</source>
                <target>Марта</target>
            </trans-unit>
            <trans-unit>
                <source>April</source>
                <target>Апреля</target>
            </trans-unit>
            <trans-unit>
                <source>May</source>
                <target>Мая</target>
            </trans-unit>
            <trans-unit>
                <source>June</source>
                <target>Июня</target>
            </trans-unit>
            <trans-unit>
                <source>July</source>
                <target>Июля</target>
            </trans-unit>
            <trans-unit>
                <source>August</source>
                <target>Августа</target>
            </trans-unit>
            <trans-unit>
                <source>September</source>
                <target>Сентября</target>
            </trans-unit>
            <trans-unit>
                <source>October</source>
                <target>Октября</target>
            </trans-unit>
            <trans-unit>
                <source>November</source>
                <target>Ноября</target>
            </trans-unit>
            <trans-unit>
                <source>December</source>
                <target>Декабря</target>
            </trans-unit>
        </body>
    </file>
</xliff>
